tabcell_score/__init__.py
tabcell_score/main.py
tabcell_score/utils.py
tabcell_score-0.1.0.dist-info/METADATA
tabcell_score-0.1.0.dist-info/WHEEL
tabcell_score-0.1.0.dist-info/top_level.txt
tabcell_score-0.1.0.dist-info/RECORD
