Metadata-Version: 2.1
Name: tabcell-score
Version: 0.1.0
Summary: Packages from Quy Nhon AI
Author: TraiPPN
Author-email: phamphungoctraivl1@gmail.com
License: Apache License 2.0
Requires-Python: >=3.7
Requires-Dist: numpy
Requires-Dist: opencv-python
